[{"id":8,"assign_task_id":0,"assign_task_title":"abc","target_date":"","shift":"Morning","machine":"dddd","description":"dddd","timefrom":"12:15 PM","timeto":"2:15 PM","spare_parts":"dddwdwd","attendby":"lognsystems@gmail.com, ","jobtype":"Repair","recordtype":"Routine","status":"In Progress","assigned_to":"","done_percentage":"0%","bu":"UT","last_edit":"2017-12-20 14:05:48"},{"id":7,"assign_task_id":0,"assign_task_title":"Task to Add Record one","target_date":"","shift":"Morning","machine":"machine one","description":"machine one is working","timefrom":"12:30 PM","timeto":"12:30 PM","spare_parts":"spare parts also good","attendby":"sharma.monika573@gmail.com, doshi.priyank@gmail.com, lognsystems@gmail.com, ","jobtype":"Repair","recordtype":"Routine","status":"New","assigned_to":"","done_percentage":"0%","bu":"UT","last_edit":"2017-12-20 12:26:37"},{"id":12,"assign_task_id":0,"assign_task_title":"Test Indo Mail ","target_date":"","shift":"NONE","machine":"Laptop","description":"MAil Testing ","timefrom":"4:45 PM","timeto":"4:45 PM","spare_parts":"parts","attendby":"sharma.monika573@gmail.com, doshi.priyank@gmail.com, lognsystems@gmail.com, ","jobtype":"IOS","recordtype":"Routine","status":"New","assigned_to":"","done_percentage":"0%","bu":"UT","last_edit":"2017-12-20 16:45:37"},{"id":18,"assign_task_id":0,"assign_task_title":"Test Indo Mail ","target_date":"","shift":"Evening","machine":"ghghgh","description":"hghgghgh","timefrom":"3:00 PM","timeto":"3:00 PM","spare_parts":"fnfnfbfb","attendby":"monika sharma, logn lsystems, monika sharma, ","jobtype":"IOS","recordtype":"History","status":"New","assigned_to":"","done_percentage":"80%","bu":"MS1","last_edit":"2017-12-28 14:55:21"},{"id":19,"assign_task_id":0,"assign_task_title":"Test Indo Mail ","target_date":"","shift":"Night","machine":"aaaaaaaaaaaaaaaaa","description":"aasasas","timefrom":"2:15 PM","timeto":"3:15 PM","spare_parts":"aaaaaaaaaaa","attendby":"monika sharma, ","jobtype":"Repair","recordtype":"Routine","status":"New","assigned_to":"","done_percentage":"0%","bu":"UT","last_edit":"2017-12-28 15:02:56"}]